LICENSE
README.md
setup.cfg
setup.py
aixcalibuha/__init__.py
aixcalibuha/data_types.py
aixcalibuha.egg-info/PKG-INFO
aixcalibuha.egg-info/SOURCES.txt
aixcalibuha.egg-info/dependency_links.txt
aixcalibuha.egg-info/requires.txt
aixcalibuha.egg-info/top_level.txt
aixcalibuha/calibration/__init__.py
aixcalibuha/calibration/calibrator.py
aixcalibuha/calibration/multi_class_calibrator.py
aixcalibuha/sensitivity_analysis/__init__.py
aixcalibuha/sensitivity_analysis/morris.py
aixcalibuha/sensitivity_analysis/sensitivity_analyzer.py
aixcalibuha/sensitivity_analysis/sobol.py
aixcalibuha/utils/__init__.py
aixcalibuha/utils/configuration.py
aixcalibuha/utils/visualizer.py
examples/__init__.py
examples/e1_A_energy_system_analysis.py
examples/e1_B_energy_system_analysis.py
examples/e2_A_optimization_problem_definition.py
examples/e2_B_optimization_problem_definition.py
examples/e3_sensitivity_analysis_example.py
examples/e4_calibration_example.py
examples/e5_automated_process.py
examples/e6_multiprocessing_calibration_example.py