Metadata-Version: 2.1
Name: aixcalibuha
Version: 0.3.0
Summary: Framework used for sensitivity-analysisand calibration for models of HVAC components.
Home-page: https://github.com/RWTH-EBC/AixCaliBuHA
Author: RWTH Aachen University, E.ON Energy Research Center, Institute of Energy Efficient Buildings and Indoor Climate
Author-email: fabian.wuellhorst@eonerc.rwth-aachen.de
License: MIT
Download-URL: https://github.com/RWTH-EBC/AixCaliBuHA/archive/refs/tags/0.3.0.tar.gz
Keywords: calibration,building,energy,black-box optimization,sensitivity_analysis
Platform: UNKNOWN
Classifier: Development Status :: 3 - Alpha
Classifier: License :: OSI Approved :: MIT License
Classifier: Topic :: Scientific/Engineering
Classifier: Intended Audience :: Science/Research
Classifier: Programming Language :: Python :: 3.7
Classifier: Programming Language :: Python :: 3.8
License-File: LICENSE
